google_auth_tpm/__init__.py
google_auth_tpm/credentials.py
google_auth_tpm-0.0.35.dist-info/LICENSE
google_auth_tpm-0.0.35.dist-info/METADATA
google_auth_tpm-0.0.35.dist-info/WHEEL
google_auth_tpm-0.0.35.dist-info/top_level.txt
google_auth_tpm-0.0.35.dist-info/RECORD
