Metadata-Version: 2.1
Name: google_auth_tpm
Version: 0.0.35
Summary: Python TPM based Credentials for Google Cloud Platform
Home-page: https://github.com/salrashid123/google-auth-library-python-tpm
Author: Sal Rashid
Author-email: salrashid123@gmail.com
Classifier: License :: OSI Approved :: Apache Software License
Classifier: Operating System :: OS Independent
Classifier: Development Status :: 3 - Alpha
Classifier: Intended Audience :: Developers
Classifier: Programming Language :: Python
Classifier: Programming Language :: Python :: 3.0
Classifier: Topic :: Software Development :: Libraries
Classifier: Topic :: Software Development :: Libraries :: Python Modules
License-File: LICENSE
Requires-Dist: google-auth >=2.34.0
Requires-Dist: tpm2-pytss >=2.3.0
